<?xml version="1.0" encoding="UTF-8"?>
<!-- =========================================================== -->
<!-- View Bean Configuration File					             -->
<!-- =========================================================== -->
<beans xmlns="http://www.springframework.org/schema/beans"
	xmlns:context="http://www.springframework.org/schema/context"
	xmlns:util="http://www.springframework.org/schema/util"
	xmlns:xsi="http://www.w3.org/2001/XMLSchema-instance"
	xsi:schemaLocation="
		http://www.springframework.org/schema/beans http://www.springframework.org/schema/beans/spring-beans-3.0.xsd
		http://www.springframework.org/schema/context http://www.springframework.org/schema/context/spring-context-3.0.xsd
		http://www.springframework.org/schema/util http://www.springframework.org/schema/util/spring-util-3.0.xsd
	">

	<bean id="freemarkerConfig" class="org.springframework.ui.freemarker.FreeMarkerConfigurationFactory">
		<property name="templateLoaderPath" value="/META-INF/freemarker/" />
	</bean>

	<bean class="com.mysql.jdbc.Driver" />
	<bean class="org.postgresql.Driver" />

	<bean id="monitor" class="org.adbcj.webasync.Monitor" lazy-init="false">
		<constructor-arg>
			<bean class="org.springframework.scheduling.concurrent.ThreadPoolTaskExecutor">
				<property name="maxPoolSize" value="2" />
				<property name="queueCapacity" value="0" />
			</bean>
		</constructor-arg>
		<constructor-arg ref="jdbcTaskExecutor" />
		<constructor-arg>
			<bean class="java.io.FileWriter">
				<constructor-arg value="/tmp/memusage.txt" />
				<constructor-arg value="true" />
			</bean>
		</constructor-arg>
		<constructor-arg>
			<bean class="java.io.FileWriter">
				<constructor-arg value="/tmp/vmstat.txt" />
				<constructor-arg value="true" />
			</bean>
		</constructor-arg>
	</bean>

	<!-- ADBCJ Netty -->
	<bean id="sessionProvider" class="org.adbcj.ConnectionPool">
		<constructor-arg>
			<bean class="org.adbcj.ConnectionManagerProvider" factory-method="createConnectionManager">
				<constructor-arg value="adbcj:mysqlnetty://localhost/adbcjtck" />
				<constructor-arg value="adbcjtck" />
				<constructor-arg value="adbcjtck" />
			</bean>
		</constructor-arg>
	</bean>

	<!-- ADBCJ JDBC -->
	<bean id="jdbcTaskExecutor" class="org.springframework.scheduling.concurrent.ThreadPoolTaskExecutor">
		<property name="maxPoolSize" value="1" />
	</bean>
	<!--TODO: We need the edquivalent of the RemotePoolSizeManager -->
	<!--

	<bean id="jdbcExecutorService" class="org.springframework.core.task.support.ExecutorServiceAdapter">
		<constructor-arg ref="jdbcTaskExecutor" />
	</bean>

	<bean id="sessionProvider" class="org.adbcj.ConnectionPool">
		<constructor-arg>
			<bean class="org.adbcj.jdbc.JdbcConnectionManager">
				<constructor-arg value="jdbc:mysql://localhost/adbcjtck" />
				<constructor-arg value="adbcjtck" />
				<constructor-arg value="adbcjtck" />
				<constructor-arg ref="jdbcExecutorService" />
				<constructor-arg><props/></constructor-arg>
			</bean>
		</constructor-arg>
	</bean>
	-->

	<bean id="dataSource" class="org.springframework.jdbc.core.simple.SimpleJdbcTemplate">
		<constructor-arg>
			<bean class="org.apache.commons.dbcp.BasicDataSource">
				<property name="driverClassName" value="com.mysql.jdbc.Driver" />
				<property name="url" value="jdbc:mysql://localhost/adbcjtck" />
				<property name="username" value="adbcjtck" />
				<property name="password" value="adbcjtck" />
				<property name="maxActive" value="100" />
			</bean>
		</constructor-arg>
	</bean>

	<!-- Netty HTTP Server stuff -->
	<bean id="executor" class="org.springframework.scheduling.concurrent.ThreadPoolExecutorFactoryBean">
		<property name="queueCapacity" value="0" />
	</bean>

	<bean id="pipelineFactory" class="org.adbcj.webasync.PipelineFactory">
		<property name="handler">
			<bean class="org.adbcj.webasync.WebHandler">
				<property name="jdbc">
					<bean class="org.adbcj.webasync.Jdbc">
						<property name="freeMarkerConfig" ref="freemarkerConfig" />
						<property name="jdbcTemplate" ref="dataSource" />
					</bean>
				</property>
				<property name="adbcj">
					<bean class="org.adbcj.webasync.Adbcj">
						<property name="freeMarkerConfig" ref="freemarkerConfig" />
						<property name="connectionPool" ref="sessionProvider" />
					</bean>
				</property>
				<property name="remotePoolSizeManager">
					<bean class="org.adbcj.webasync.RemotePoolSizeManager">
						<property name="connectionPool" ref="sessionProvider" />
						<property name="monitor" ref="monitor" />
					</bean>
				</property>
			</bean>
		</property>
	</bean>

	<bean id="bootstrap" class="org.jboss.netty.bootstrap.ServerBootstrap">
		<constructor-arg>
			<bean class="org.jboss.netty.channel.socket.nio.NioServerSocketChannelFactory">
				<constructor-arg ref="executor" />
				<constructor-arg ref="executor" />
			</bean>
		</constructor-arg>
		<property name="pipelineFactory" ref="pipelineFactory" />
	</bean>


</beans>
